{"query": "Flow alternative", "follow_up_questions": null, "answer": null, "images": [], "results": [{"url": "https://www.producthunt.com/products/flow-2/alternatives", "title": "Flow Competitors & Alternatives (2026) | Product Hunt", "content": "Subscribe\n\nSocialFacebookWellfoundX\n\n# FlowAlternatives\n\nLooking beyond Flow’s collaborative workspace? Try Linear for lightning-fast issue tracking, Jira for robust, enterprise workflows, and Trello if you love simple Kanban boards. For deeper planning, Asana brings timelines and automation, while ClickUp unifies docs, goals, and tasks—flexible enough to replace multiple tools.\n\n## Alternatives Discussion\n\nGeneral\n\np/general\n\nby\n\n•\n\nWhat task management software are you using?\n\n42\n\nShow more forum threads\n\n## Alternative Products\n\nMost relevant\n\nElevenAgents by ElevenLabs\n\nElevenAgents by ElevenLabsScale conversations without scaling your team\n\nPromoted\n\nTrello\n\nTrelloVisual collaboration with a shared perspective on projects\n\n4.8 (116 reviews)\n\nProject management software\n\n• [...] Subscribe\n\nFlow\n\n## Team's work, projects & tasks in one collaborative workspace\n\n70 followers\n\n## Team's work, projects & tasks in one collaborative workspace\n\n70 followers\n\nVisit website\n\nProductivity\n\n•\n\nProject management software\n\n•\n\nTeam collaboration software\n\nSimple task tracking and project management software for teams. Plan projects, prioritize to-dos and delegate tasks. Sign up for a free trial today.\n\n Overview\n Launches5\n Reviews\n Alternatives\n Team\n Awards\n More\n\nSubscribe\n\nSocialFacebookWellfoundX\n\n# FlowAlternatives [...] 4.8 (116 reviews)\n\nProject management software\n\n•\n\nTeam collaboration software\n\n•\n\nIssue tracking software\n\nAsana\n\nAsanaTrack, manage, and connect your projects across any team\n\n4.6 (83 reviews)\n\nProject management software\n\n•\n\nTeam collaboration software\n\n•\n\nIssue tracking software\n\nTodoist\n\nTodoistThe to-do list to organize work & life\n\n4.8 (53 reviews)\n\nProductivity\n\n•\n\nProject management software\n\n•\n\nCalendar apps\n\nZenkit\n\nZenkitProject management made easy. \n\n4.8 (8 reviews)\n\nProductivity\n\n•\n\nProject management software\n\n•\n\nTeam collaboration software\n\nBordio\n\nBordioManage all your tasks & events on one single board\n\n5.0 (4 reviews)\n\nProject management software\n\nTeamhood\n\nTeamhoodThe better way to manage projects and teamwork\n\n5.0 (3 reviews)\n\nProject management software\n\n•", "score": 0.7997713, "raw_content": null}, {"url": "https://pixverse.ai/en/blog/google-flow-alternative", "title": "Best Google Flow Alternatives for AI Video in 2026 | PixVerse", "content": "## Conclusion\n\nThe best Google Flow alternative is not just the tool with the prettiest demo. It is the tool that helps you turn an idea into a usable video with enough control, credits, consistency, and workflow flexibility to keep creating after the first test.\n\nGoogle Flow is a strong option for creators who want Google’s AI filmmaking ecosystem. PixVerse, Runway, Kling, Luma, Hailuo, Pika, MagicLight, and ImagineArt each solve a different version of the replacement problem.\n\nSo try the astronaut pancake shot in two or three tools. Judge the thing that actually matters: which one gets you from “that would be fun” to a clip you can share, pitch, edit, or ship. [...] User feedback: Users often praise Pika’s creativity and accessibility, but review sites and community discussions also show frustration around subscription value, credits, and inconsistent generations.\n\nWhy it works as a Google Flow alternative: Pika is a good alternative when you want fast creative energy, stylized effects, and social-native experimentation instead of a Google-centered filmmaking suite.\n\n### 7. MagicLight AI - Best for Long-Form Story and Script Workflows\n\nProduct intro: MagicLight AI is closer to a script-to-video and story-video platform than a single-shot AI video generator. Its own Google Flow alternative article emphasizes long-form content, scripts, voices, multilingual output, and story-style workflows.\n\nPros: [...] This article focuses on the AI video meaning. If you searched “google flow free alternative” or “alternative to google flow text to video,” you are in the right place.\n\n## Quick Comparison Table\n\nAs of May 21, 2026, Google positions Flow as an AI filmmaking tool designed around Veo, Imagen, and Gemini in its official Flow launch post. Google also updated the Flow family with Gemini Omni, Flow Agent, custom Flow Tools, and mobile apps in its May 2026 Flow update. That makes Flow a strong creative suite, not just a prompt box.\n\nAlternatives matter when you want different model choices, broader access, simpler pricing, different creative controls, script-to-video workflows, or a tool that fits your team better.", "score": 0.7646988, "raw_content": null}, {"url": "https://github.com/zachlatta/freeflow", "title": "GitHub - zachlatta/freeflow: Free & fast alternative to Wispr Flow · GitHub", "content": "FreeFlow icon\n\nFreeFlow icon\n\n# FreeFlow\n\nFree and open source alternative to Wispr Flow, Superwhisper, and Monologue.\n\n⬇ Download FreeFlow.dmg  \nWorks on all Macs (Apple Silicon + Intel)\n\nFreeFlow demo\n\nFreeFlow demo\n\nThank you to @marcbodea for maintaining FreeFlow!\n\n## Overview\n\nFreeFlow is a free Mac dictation app inspired by Wispr Flow, Superwhisper, and Monologue. It gives you fast AI transcription, context-aware cleanup, and voice-driven text editing without a monthly subscription.\n\n## Quick Start\n\n`Fn`\n`Command-Fn`\n\n## Features\n\n## Edit Mode [...] `You are a dictation post-processor. You receive raw speech-to-text output and return clean text ready to be typed into an application.\nYour job:\n- Remove filler words (um, uh, you know, like) unless they carry meaning.\n- Fix spelling, grammar, and punctuation errors.\n- When the transcript already contains a word that is a close misspelling of a name or term from the context or custom vocabulary, correct the spelling. Never insert names or terms from context that the speaker did not say.\n- Preserve the speaker's intent, tone, and meaning exactly.\nOutput rules:\n- Return ONLY the cleaned transcript text, nothing else. So NEVER output words like \"Here is the cleaned transcript text:\"\n- If the transcription is empty, return exactly: EMPTY [...] Only positive values are used. Remove a custom timeout to return to the 20-second default:\n\n## License\n\nLicensed under the MIT license.\n\n## About\n\nFree & fast alternative to Wispr Flow\n\n### Resources\n\n### License\n\n### Uh oh!\n\nThere was an error while loading. Please reload this page.\n\nThere was an error while loading. Please reload this page.\n\n### Stars\n\n### Watchers\n\n### Forks\n\n## Releases 87\n\n## Packages 0\n\n### Uh oh!\n\nThere was an error while loading. Please reload this page.\n\nThere was an error while loading. Please reload this page.\n\n## Contributors\n\n### Uh oh!\n\nThere was an error while loading. Please reload this page.\n\nThere was an error while loading. Please reload this page.\n\n## Languages\n\n## Footer\n\n### Footer navigation", "score": 0.63179934, "raw_content": null}, {"url": "https://flow-like.com", "title": "Flow-Like — Open-Source Company Platform for Data, AI, Automation & Apps", "content": "business hobbyist\n\nZapier and Make are cloud-only SaaS automation tools. Flow-Like is open-source, self-hostable, and runs offline. It also goes beyond automation: you can build BI dashboards, AI agents, data pipelines, and full applications on the same canvas. If you need a free, self-hosted alternative with more power, Flow-Like is worth evaluating.\n\nCan we migrate existing automations? enterprise developer \n\nenterprise developer\n\nYes. Our onboarding includes migration support for RPA bots, Python scripts, and orchestration tools. We'll audit, document, and convert your highest-value workflows.\n\nStart Building Solutions\n\n## What would you build if the platform wasn't the bottleneck? [...] Download the Studio and start building — locally, offline, no account required. Or jump into the web app. Free workflow automation for individuals, forever.\n\nFree forever. No account. Works offline.\n\nDownload Studio — Free\n\nCollaborate on the web app or self-host.\n\nOpen Web App\n\nDedicated support. Custom SLA. On-premise.\n\nBook a Call\n\nFull source code. Full SDK. Full API docs.\n\nView on GitHub [...] ### The Rust Workflow Engine\n\n~0.6ms execution, 244k events/second\n\nCompiled Rust workflow engine running a typed DAG with Protobuf serialization. File-based projects on an object store abstraction — local filesystem, S3, R2, GCP, or Azure Blob.\n\n~0.6ms per execution. 244k events/second. Your infrastructure costs drop — or you don't need much infrastructure at all.\n\nCustom nodes run in WebAssembly (WASM) sandboxes for isolation and security. The visual editor is your entry point, but there's no ceiling.\n\n→ Architecture deep-dive for CTOs & tech leads\n\nCompiled Rust Typed DAG Protobuf WebAssembly Sandboxing\n\nTrusted in Production\n\n## Open-source and self-hosted. Genuinely.", "score": 0.38699567, "raw_content": null}, {"url": "https://www.epicflow.com", "title": "Project Resource Management Software - Epicflow", "content": "![15 Best Resource Management Tools & Software ](\nBest Microsoft Project Alternatives in 2026: Tools for Optimizing Delivery and Maximizing Business Value\nBest Microsoft Project Alternatives in 2026: Tools for Optimizing Delivery and Maximizing Business Value\nCrowd Award Logo | Epicflow\nCrowd Award Logo | Epicflow\nSoftwareworld Award Logo | Epicflow\nSoftwareworld Award Logo | Epicflow\nHigh Performer Summer Award Logo | Epicflow\nHigh Performer Summer Award Logo | Epicflow\nCrozdesk Award Logo | Epicflow\nCrozdesk Award Logo | Epicflow\nBritish MoD | Epicflow\nBritish MoD | Epicflow\nJoscar 2024 | Epicflow\nJoscar 2024 | Epicflow\nJoscar 2024 | Epicflow\nJoscar 2024 | Epicflow\nDutch MoD | Epicflow\nDutch MoD | Epicflow", "score": 0.18705876, "raw_content": null}], "response_time": 1.87, "request_id": "a52ba812-dbde-41d4-8287-5e1ad16776bc"}