{"query": "Focus with others through synchronized Pomodoro sessions complaints OR frustrating OR broken", "follow_up_questions": null, "answer": null, "images": [], "results": [{"url": "https://apps.apple.com/us/app/session-pomodoro-focus-timer/id1521432881?see-all=reviews&platform=mac", "title": "‎Session Pomodoro Focus Timer - Ratings & Reviews - App Store", "content": "give to others.There are few things user experience-wise that might be improved. For example, during breaks, you can write what you plan to work on next session. When you change this stuff, it doesn't seem to stick once you actually get started. The calendar integration is nice, expecially for reviewing your previous work, but it's not perfect. I would like to see a way to export notes and maybe some rich text formatting would be nice. But these are minor requests. In addition, a smaller ui when you don't need to adjust any settings, but still want the timer on top of all windows for quick access.It's a good app, and the best of its kind I've found so far. I was debating buying a physical timer but have found Session to work just as well, and probably better. I also like the default [...] give to others.There are few things user experience-wise that might be improved. For example, during breaks, you can write what you plan to work on next session. When you change this stuff, it doesn't seem to stick once you actually get started. The calendar integration is nice, expecially for reviewing your previous work, but it's not perfect. I would like to see a way to export notes and maybe some rich text formatting would be nice. But these are minor requests. In addition, a smaller ui when you don't need to adjust any settings, but still want the timer on top of all windows for quick access.It's a good app, and the best of its kind I've found so far. I was debating buying a physical timer but have found Session to work just as well, and probably better. I also like the default [...] I've recently been having trouble focusing during my work time when a friend recommended Session. After using it one day, I knew i loved it! The free version is a must-have but i would highly recommend supporting the developer and paying for Pro.There are many excellent features for this app: - The app is beautifully designed, intuitive, and user friendly. - It integrates with your calendar which is really excellent. - While you're focusing, a ticking sound plays (it can be turned off) but i find that it's helps with my focus. The ocean sounds that play during break are also nice. - There's a breathing exercise before the focus session. - The notes section which is visible during the focus session is very helpful for getting your thoughts down.- After a session is complete, you're", "score": 0.46905875, "raw_content": null}, {"url": "https://www.youtube.com/watch?v=5WRO79zuJ4U", "title": "The Danger of the Pomodoro Method (why most people are using it wrong)", "content": "enough time to shower so I can get changed and\nget back to my Pomodoro.\" No, no, no, no. Just use the Pomodoro\nmethod during break time. It's okay to take a one or two hour break to go to the gym or to have lunch. These are normal human things. Don't kill yourself here. But when you are in a Pomodoro session, you should stay focused. Trust me, if you are using\nthe Pomodoro method correctly, you will have more than enough\nfocus time during the day. (smooth jazz music) Tip number three is personalize the timing of your Pomodoro sessions. The timing doesn't have to be 25 minutes and a five minute break. I don't know why that's\nbecome the cult of timing. Any times, it seems between\nthe 20 and 60 minute mark for your focus sessions are fine. You need to figure out what [...] in front of me that says, listen you have 10 minutes\ngo, don't break it. Cuz real thing is there. Big brother is watching. Importantly, also this removes another potential for distraction. If you have the timer on\nyour computer or your phone, you might more likely look at that and then get distracted or\npulled into something else, even if the only thing you\ndo is make studying nicer, it's a small price to pay\nfor making, studying nicer especially when you're studying maybe five to 10 hours a day. (smooth jazz music) The next tip is remove\nall possible distractions. Eliminate the possibility of being distracted during\nyour Pomodoro sessions. Please remove all unnecessary\nitems from your desk, all books that you're not using, all notes that you're not gonna be using, your phone especially, [...] computer, it's study time. When you're in your Pomodoro sessions, you're signaled unconsciously,\nif you do it enough, that this is study time. Again, this is the most vital\ntip of this entire video. If it is study time, if you\nare in a Pomodoro session, you must stay focused. Oh, and this applies to your breaks too. When it's break time, go take a break. Don't study during your break time, cuz that would mess things up. Again, if you're gonna study\nthrough your break time make it another Pomodoro session. That way you're extending your flow and not messing with\nclassical conditioning. (smooth jazz music) Okay, three more tips here. And the third to last tip is music. Use it correctly for you. Music is a tough topic around studying. There's no strong answers. There's no strong decision", "score": 0.4177708, "raw_content": null}, {"url": "https://www.youtube.com/watch?v=4bD_lKWBTlI", "title": "The Problem With The Pomodoro Technique 🕔", "content": "be interrupted when you're in a flow state and you're not pushing yourself to work through these 25 minute intervals when you don't really feel like working in anticipation of the break from the timer let us know if there are any focus methods that you're currently trying out and how it's been helping you we'd love to hear from you guys until next time bye [...] when i had these assignments that were really big and i had to really put in my thinking cap and get to the nitty-gritty of problem solving this is because when i wanted to use my brain for heavy lifting and i was using the pomodoro method at the same time i found that it would often interrupt my workflow when i was doing these 30 minutes to an hour intervals for example if i'm ideating and brainstorming for my next creative project i'm on a roll and my brain is in this complete state of focus however in the moment that the pomodoro timer sets off i've conditioned myself to kind of let go of that concentration and take the time to relax and sit back i'll just be scrolling on my phone maybe doing another task in between and sometimes i'll go back to the project at hand or i just won't come [...] i have an issue with the pomodoro timer let me tell you why the pomodoro technique consists of working in typically 25 minute intervals and allowing yourself to have quick breaks in between a lot of people find it effective because it allows for you to stay hyper focused and free of distractions when i first heard about this method in high school i thought it was super effective and it allowed for me to power through huge chunks of when i would be studying for tests or exams but it was only effective up to a certain point although it was effective for periods when i was doing menial tasks that i didn't really want to do or studying for exams i found that it wasn't necessarily the best for when i wanted to do like creative work or when i had these assignments that were really big and i had", "score": 0.348934, "raw_content": null}, {"url": "https://www.arcusvision.app/blog/pomodoro-technique-is-broken", "title": "Why the Pomodoro Technique Fails and How Intelligent Focus Mode Fixes It | ArcusVision", "content": "ArcusVision Logo\n\nArcusVision\n\nGet Started\n\nProductivity7 min read\n\n# The Pomodoro Technique is Broken. Here's What We Built Instead.\n\n## Quick Summary\n\n### What is wrong with the standard Pomodoro Technique?\n\nThe Pomodoro Technique provides a timer but assumes you have already solved the hardest productivity problem: deciding what to work on. For people with goals across multiple life areas, the decision of what to focus on causes decision fatigue and often leads to working on the wrong things.\n\n### How does ArcusVision's Focus Mode improve on Pomodoro? [...] The Pomodoro Technique breaks down when:\n\n1. You have goals across multiple areas of life competing for your time\n2. You spend more time deciding what to work on than actually working\n3. You finish Pomodoro sessions feeling productive but later realize you worked on the wrong things\n4. You have no data on whether your daily work is aligned with your long-term goals\n\nIf any of those describe your situation, the problem is not focus. It is task selection. And that is the problem Focus Mode was built to solve.\n\n## Try It\n\nArcusVision is free during early access. Focus Mode is available immediately after you create your first goal and generate a roadmap. The algorithm needs at least a few tasks to score, but you will see recommendations from your very first session. [...] But the Pomodoro Technique has a critical blind spot. It assumes you have already solved the hardest problem in productivity: deciding what to work on.\n\nThink about how most Pomodoro sessions actually start. You open your timer app, and then you spend five minutes scanning your task list, trying to figure out what deserves your attention. Is it the report that is due Friday? The code review your teammate asked about? The course module you have been procrastinating on? The habit you promised yourself you would build?\n\nBy the time you decide, you have already burned mental energy on the decision itself. And there is no guarantee you chose the right thing. The Pomodoro Technique is a timing mechanism. It is not a decision-making tool.\n\n## The Real Bottleneck is Not Focus. It is Selection.", "score": 0.34323218, "raw_content": null}, {"url": "https://unito.io/blog/best-pomodoro-apps", "title": "7 Pomodoro Apps To Get More Done Without Burning Out", "content": "You can customize the length of your sessions and breaks directly from the desktop timer, though it doesn’t seem like there’s a way to customize the length of your long breaks. In fact, the app doesn’t even have long breaks. Where other Pomodoro timers automatically cycle to the long break after four Pomodoro sessions, Focus Booster doesn’t.\n\nFocus Booster switches between timers automatically by default. This raises the same problem I mentioned before; you feel rushed to take your break, and it doesn’t reflect the reality of your work situation. Unlike the other apps on this list, though, you can’t turn this off. [...] ### Pricing\n\nOtto is 100% free.\n\n### Biggest drawback\n\nThe Otto app can be a little rough around the edges at times. I’ve run into a few bugs, like Pomodoro sessions starting or stopping without my intervention. A refresh usually fixes any issues, and they’re infrequent enough to not affect me most of the time. Still, it’s something to keep an eye out for while you work.\n\n## Focused Work\n\nFocused Work is available for iPhones, Macs, and iPads. It combines a simple Pomodoro timer with analytics and other productivity methods.\n\n### Features [...] Focused Work is designed more closely to a Tabata or other fitness timer than other Pomodoro apps. This gives you the flexibility to build your own focus sessions. Whether you’re customizing a session or choosing a pre-built option like Pomodoro, setting and running these sessions is a breeze.\n\nBeyond the timer itself, Focused Work also boasts productivity analytics. You can track the number of focus sessions you complete in a day, the amount of focus time you have in a day, and the amount of break time, all against goals you set for yourself. You can also use bar graphs to see the amount of focus and break time and track your productivity over the week.", "score": 0.2844075, "raw_content": null}], "response_time": 2.47, "request_id": "86ab7c9a-c7d0-463d-9aea-869347949f21"}