{"query": "OPD-Evolver complaints OR frustrating OR broken", "follow_up_questions": null, "answer": null, "images": [], "results": [{"url": "https://arxiv.org/abs/2606.17628", "title": "OPD-Evolver arXiv paper", "content": "OPD-Evolver Cultivating Holistic Agent Evolver via On-Policy Distillation.", "score": 0.1569174, "raw_content": null}, {"url": "https://www.honestgamers.com/9798/playstation-2/red-dead-revolver/review.html", "title": "Red Dead Revolver frustrating review", "content": "Intermittent reinforcement makes frustrating game hard to quit.", "score": 0.09986474, "raw_content": null}, {"url": "https://support.google.com/googleplay/android-developer/thread/303210318/app-rejected-due-to-broken-functionality-policy", "title": "App rejected Broken Functionality policy", "content": "App rejected due to broken functionality unclear reason.", "score": 0.04952013, "raw_content": null}, {"url": "https://groups.google.com/g/google-admob-ads-sdk/c/-XO-RZn6uvc", "title": "Broken Functionality policy violation", "content": "App does not open or load Play Store rejection.", "score": 0.032298584, "raw_content": null}, {"url": "https://www.cipherhealth.com", "title": "Reduce patient complaints by 70%", "content": "CipherHealth patient complaints reduction platform.", "score": 0.030171758, "raw_content": null}], "response_time": 0.0, "request_id": "7f9d3e55-2170-4787-a628-30024fab5dfc"}