{"query": "PH Daily Top 50 complaints OR frustrating OR broken", "follow_up_questions": null, "answer": null, "images": [], "results": [{"url": "https://tribune.net.ph/amp/story/2026/05/05/lto-tops-list-of-most-complaint-govt-agenciesarta", "title": "LTO Tops List of Most Complained Government Agencies in Philippines, Says ARTA | Daily Tribune", "content": "Trailing the LTO is the Bureau of Internal Revenue with 89 complaints, with 11 active and 78 resolved; Food and Drug Administration with 62 complaints, 23 are active complaints, while 39 are closed; Land Registration Authority (Registry of Deeds) with 55 complaints, 19 of which are active, and 36 complaints are resolved; and Philippine Statistics Authority with 49 complaints, 11 active and 38 resolved.\n\nFor the government-owned and controlled corporations with the largest number of complaints, the Social Security System (SSS) topped the list with 156 complaints, 44 active and 112 closed.\n\nFollowing the SSS are Pag-IBIG Fund, PhilHealth, Philippine Postal Corporation, and Landbank of the Philippines. [...] ## Suggested Articles\n\nFuel costs squeeze contractors\n\n### Fuel costs squeeze contractors\n\nPersistently high fuel prices are putting increasing financial pressure on construction firms, with one contractor…\n\nJasper Dawang·2 hours ago\n\nGroup vows more DPWH complaints\n\n### Group vows more DPWH complaints\n\nILOILO CITY — An Antique-based civic and environmental advocacy group said the complaints it filed before the Office of…\n\nFraye Cedrick Anona·2 hours ago\n\np91.2-M van bid faces dispute\n\n### p91.2-M van bid faces dispute\n\nA ₱P91.2-million procurement for 80 vans for deployment to barangays in Laoag City has sparked a legal dispute after…\n\nJasper Dawang·3 hours ago\n\nDA suspends Iloilo rice imports\n\n### DA suspends Iloilo rice imports [...] # Daily TribuneDaily TribuneDaily Tribune\n\nDaily Tribune\nDaily Tribune\nDaily Tribune\nDaily Tribune\nDaily Tribune\nDaily Tribune\n\nThe Philippines' leading digital newspaper.\n\nCompany\n\n© 2026 Daily Tribune · tribune.net.ph · Powered by Quintype\n\n# LTO tops list of most-complaint gov't agencies—ARTA\n\nRaffy Ayeng·5 May 2026, 7:01 pm·1 min read\n\nShare\n\nLTO tops list of most-complaint gov't agencies—ARTA\n\nPhotograph courtesy of PNA\n\nWhat's your take?\n\nShare\n\nGoogle Preferred Sources\n\nGet more Daily Tribune stories in your search results\n\nAdd Daily Tribune as a preferred source on Google Search.\n\nContinue reading\n\n4 cops relieved over wrong arrest\nDrug ops net 3 individuals\nDILG pushes safe spaces enforcement\n\n## Suggested Articles\n\nFuel costs squeeze contractors", "score": 0.5513086, "raw_content": null}, {"url": "https://www.wavetec.com/blog/most-common-customer-complaints-and-solutions", "title": "10 Most Common Customer Complaints (With Examples & Solutions)", "content": "### 5. Repetitive Information Requests\n\nCustomers often find it frustrating to repeatedly provide the same personal information, account details, or case history. This is especially common in healthcare, banking, and customer support interactions, where inefficient data systems lead to unnecessary repetition.\n\nTo solve this issue, businesses can integrate self-check-in kiosks and CRM systems that allow customers to pre-fill or verify their details once, eliminating the need to repeat information.\n\nFor example, many healthcare facilities now use kiosks where patients can scan their IDs to check in rather than filling out paper forms multiple times. This speeds up the process, reduces frustration, and enhances the customer experience. [...] Currently deployed in over 100 branches, with 200 more in progress, this solution has significantly improved service quality while minimizing customer frustration.\n\nBy using the best queue management system, banks, and other service-driven businesses can create a more seamless and organized service experience while optimizing operational workflows.\n\n### 2. Lack of Communication or Information\n\nNearly 60% of customers say long holds and wait times are the most frustrating parts of a service experience. When customers are left in the dark about their service status, next steps, or delays, this uncertainty leads to frustration and dissatisfaction.\n\nImplementing digital signage, SMS notifications, and automated updates can help keep customers informed in real-time. [...] The solution is to implement centralized reporting and standardized workflows using digital tools. Many banks use Wavetec’s dashboards to monitor service times across all locations, ensuring that each branch adheres to uniform Service Level Agreements (SLAs).\n\nBy maintaining consistency, businesses can deliver predictable and reliable service, no matter where the customer interacts.\n\n### 9. Inconvenient Appointment Scheduling\n\ninconvenient-appointment-scheduling\n\ninconvenient-appointment-scheduling\n\nLong wait times are frustrating, but so is an inefficient appointment booking system. Frustration builds when customers struggle to find available slots or go through complex scheduling processes.", "score": 0.25520253, "raw_content": null}, {"url": "https://newsinfo.inquirer.net", "title": "Philippines Top Stories: Politics, Environment, Education ...", "content": "Subscribe to our newsletter!\n\nStay informed with our daily news and weekend roundup delivered straight to your inbox!\n\nYour subscription could not be saved. Please try again.\n\nYour subscription has been successful.\n\nVideos\n\nYour subscription could not be saved. Please try again.\n\nYour subscription has been successful.\n\n###### TRENDING\n\n## Cayetano answers complaint over Dela Rosa's 'escape' – Ombudsman\n\n## Ex-NBI chief: ‘Oplan Romanov’ a threat vs Marcoses, not VP Duterte\n\n## ‘Is there a deal?’: Cayetano to back SEA Games probe but sets a condition\n\n## Sherwin Gatchalian says he's hurt, insulted by online memes\n\n## Matibag says Pia Cayetano's remark ‘more frightening for me’\n\nMETRO\n\n# E. Rodriguez Ave. in QC to have partial lane closure for repairs\n\nJUL 16 - 05:16PM [...] JUL 16 - 05:16PM\n\n# Motorcycle taxi rider stabbed dead in Caloocan\n\nJUL 16 - 04:12PM\n\n# Manila Water’s Cardona treatment plant boosts supply, a key source for Rizal\n\nJUL 15 - 10:20PM\n\nmore stories\n\nREGIONS\n\n# Memorial to 1990 quake soon to rise in Baguio\n\nJUL 17 - 05:06AM\n\n# Mayon’s rumbling stirs fear among Albay folk\n\nJUL 17 - 05:04AM\n\n# Conservationists seek deeper probe of PH eagle shooting\n\nJUL 17 - 05:02AM\n\nmore stories\n\nNATION\n\n# Increase in taxes pushed to protect youth from vices\n\nJUL 17 - 05:52AM\n\n# NFA hikes palay buying price to P21\n\nJUL 17 - 05:50AM\n\n# MMDA’s Go has got to go, say lawmaker, teachers\n\nJUL 17 - 05:48AM\n\nmore stories\n\nENVIRONMENT\n\n# Philippine Eagle Sawaga-Dalwangan shows major recovery—PEF\n\nJUL 16 - 02:21PM [...] featured image right top story\n\n## Taal Volcano logs second phreatomagmatic eruption this monthJuly 17, 2026\n\nfeatured image right top story\n\nLATEST NEWS\n\n# Pagasa: Fair weather, isolated rain showers until weekend\n\nJULY 17, 2026\n\n# P3.74M ‘shabu’ seized in Camarines Sur buy-bust\n\nJULY 17, 2026\n\n# 400 entrepreneurs join Bicol MSME summit\n\nJULY 17, 2026\n\n# ‘Reformed’ drug personality yields over P700,000 worth of meth in Iloilo\n\nJULY 17, 2026\n\n# Ejercito pushes long-term infra master plan to stimulate growth\n\nJULY 16, 2026\n\n# Groups expand health initiative in ‘underserved’ Eastern Samar towns\n\nJULY 16, 2026\n\n# Ombudsman welcomes DMW’s bid to appeal Ignacio’s junked plunder case\n\nJULY 16, 2026\n\n# Negros solon pays tribute to slain scientist’s professional feats\n\nJULY 16, 2026", "score": 0.19650257, "raw_content": null}, {"url": "https://cri.org/reports/broken-promises", "title": "“Broken Promises” - Climate Rights ...", "content": "Philippines government is failing its obligations to fully enforce environmental laws. [...] Despite ongoing complaints from local communities, those directly impacted face a lack of accountability and remedies for the harms they have suffered. People interviewed by Climate Rights International reported that nickel mining is causing excessive pollution and that the Philippines government — in particular the Department of Environment and Natural Recourses and its Mines and Geosciences  Bureau — is failing its obligations to fully enforce environmental laws. In both Dinagat Island and Surigao del Sur, community members believe that some of their elected politicians, including barangay captains, mayors, and governors, accepted bribes from mining companies to approve permits, and otherwise financially benefited from mining.\n\nCorporate Responsibility [...] In late 2021, Super Typhoon Odette, a Category 5 storm, rocked the Caraga and Southern Leyte regions of the Philippines, bringing torrential rain, landslides, and storm surges that killed more than 400 people and temporarily displaced hundreds of thousands.49)Internationally, the storm was named Typhoon Rai but is recognized as Super Typhoon Odette in the Philippines. UNHCR, “Super Typhoon Rai (Odette),” n.d.  (accessed March 7, 2025). A recent study found that both extreme rainfall and wind speeds in the Philippines due to storms like Odette have become significantly more likely and intense due to climate change.50)In October 2025, survivors of Super Typhoon Odette sued Shell for damages linked to the storm and its role in contributing to the climate crisis. Greenpeace Philippines,", "score": 0.18242586, "raw_content": null}, {"url": "https://www.mayoclinic.org/diseases-conditions/depression/symptoms-causes/syc-20356007", "title": "Depression (major depressive disorder) - Symptoms and causes", "content": "Feelings of sadness, tearfulness, emptiness or hopelessness\n   Angry outbursts, irritability or frustration, even over small matters\n   Loss of interest or pleasure in most or all normal activities, such as sex, hobbies or sports\n   Sleep disturbances, including insomnia or sleeping too much\n   Tiredness and lack of energy, so even small tasks take extra effort\n   Reduced appetite and weight loss or increased cravings for food and weight gain\n   Anxiety, agitation or restlessness\n   Slowed thinking, speaking or body movements\n   Feelings of worthlessness or guilt, fixating on past failures or self-blame\n   Trouble thinking, concentrating, making decisions and remembering things\n   Frequent or recurrent thoughts of death, suicidal thoughts, suicide attempts or suicide [...] Depression is a mood disorder that causes feelings of sadness that won't go away. Unfortunately, there's a lot of stigma around depression. Depression isn't a weakness or a character flaw. It's not about being in a bad mood, and people who experience depression can't just snap out of it. Depression is a common, serious, and treatable condition. If you're experiencing depression, you're not alone. It honestly affects people of all ages and races and biological sexes, income levels and educational backgrounds. Approximately one in six people will experience a major depressive episode at some point in their lifetime, while up to 16 million adults each year suffer from clinical depression. There are many types of symptoms that make up depression. Emotionally, you may feel sad or down or [...] Certain personality traits, such as low self-esteem and being too dependent, self-critical or pessimistic\n   Traumatic or stressful events, such as physical or sexual abuse, the death or loss of a loved one, a difficult relationship, or financial problems\n   Blood relatives with a history of depression, bipolar disorder, alcoholism or suicide\n   Being lesbian, gay, bisexual or transgender, or having variations in the development of genital organs that aren't clearly male or female (intersex) in an unsupportive situation\n   History of other mental health disorders, such as anxiety disorder, eating disorders or post-traumatic stress disorder\n   Abuse of alcohol or recreational drugs\n   Serious or chronic illness, including cancer, stroke, chronic pain or heart disease", "score": 0.04794482, "raw_content": null}], "response_time": 2.93, "request_id": "d5a246e1-118b-4b1c-9515-03426f74cb89"}